{
  "data": {
    "meta": {
      "adoptsFrom": {
        "name": "SkillPlusMarkdown",
        "module": "https://app.boxel.ai/catalog/skill-plus"
      }
    },
    "type": "card",
    "attributes": {
      "cardTitle": "Calling Commands",
      "cardDescription": "Reference guide for the correct JSON structure when invoking Boxel commands",
      "cardInfo": {
        "notes": null,
        "name": "Calling Commands",
        "summary": "Reference guide for the correct JSON structure when invoking Boxel commands",
        "cardThumbnailURL": null
      },
      "commands": []
    },
    "relationships": {
      "cardInfo.theme": {
        "links": {
          "self": "https://app.boxel.ai/catalog/Theme/cardstack"
        }
      },
      "instructionsSource": {
        "links": {
          "self": "./env-calling-commands.md"
        },
        "data": {
          "type": "file",
          "id": "./env-calling-commands.md"
        }
      }
    }
  }
}
